Metadata-Version: 2.1
Name: cicd-test-ziyan
Version: 0.1.1
Summary: Facebook Private Computation Service
Home-page: https://github.com/facebookresearch/FBPCS
Author: Facebook
Author-email: researchtool-help@fb.com
License: UNKNOWN
Platform: UNKNOWN
Requires-Python: >=3.8
Requires-Dist: boto3 (==1.11.11)
Requires-Dist: dataclasses-json (==0.5.2)
Requires-Dist: pyyaml (==5.4.1)
Requires-Dist: tqdm (==4.55.1)
